trasher/__init__.py
trasher/__main__.py
trasher/cli.py
trasher/trash.py
trasher-0.1.0.dist-info/METADATA
trasher-0.1.0.dist-info/WHEEL
trasher-0.1.0.dist-info/entry_points.txt
trasher-0.1.0.dist-info/top_level.txt
trasher-0.1.0.dist-info/RECORD
