Metadata-Version: 2.4
Name: trasher
Version: 0.1.0
Summary: A safer rm replacement for macOS that moves files to Trash.
Author: lowercaseLabs
License: Proprietary
Requires-Python: >=3.9
Requires-Dist: rich>=13.7.0
Requires-Dist: typer>=0.12.0
